[
  {"stage": 6, "pattern": "123456", "description": "123456 (Rounds)"},
  {"stage": 6, "pattern": "654321", "description": "654321 (Backrounds)"},
  {"stage": 6, "pattern": "213456", "description": "rounds near miss"},
  {"stage": 6, "pattern": "132456", "description": "rounds near miss"},
  {"stage": 6, "pattern": "124356", "description": "rounds near miss"},
  {"stage": 6, "pattern": "123546", "description": "rounds near miss"},
  {"stage": 6, "pattern": "123465", "description": "rounds near miss"},
  {"stage": 6, "pattern": "564321", "description": "backrounds near miss"},
  {"stage": 6, "pattern": "645321", "description": "backrounds near miss"},
  {"stage": 6, "pattern": "653421", "description": "backrounds near miss"},
  {"stage": 6, "pattern": "654231", "description": "backrounds near miss"},
  {"stage": 6, "pattern": "654312", "description": "backrounds near miss"},
  {"stage": 6, "pattern": "124365", "description": "Rounds pair swaps"},
  {"stage": 6, "pattern": "213465", "description": "Rounds pair swaps"},
  {"stage": 6, "pattern": "214356", "description": "Rounds pair swaps"},
  {"stage": 6, "pattern": "214365", "description": "Rounds pair swaps"},
  {"stage": 6, "pattern": "563412", "description": "Backrounds pair swaps"},
  {"stage": 6, "pattern": "563421", "description": "Backrounds pair swaps"},
  {"stage": 6, "pattern": "564312", "description": "Backrounds pair swaps"},
  {"stage": 6, "pattern": "653412", "description": "Backrounds pair swaps"},
  {"stage": 6, "pattern": "126543", "description": "4-bell run step pairs"},
  {"stage": 6, "pattern": "216543", "description": "4-bell run step pairs"},
  {"stage": 6, "pattern": "345612", "description": "4-bell run step pairs"},
  {"stage": 6, "pattern": "345621", "description": "4-bell run step pairs"},
  {"stage": 6, "pattern": "432156", "description": "4-bell run step pairs"},
  {"stage": 6, "pattern": "432165", "description": "4-bell run step pairs"},
  {"stage": 6, "pattern": "561234", "description": "4-bell run step pairs"},
  {"stage": 6, "pattern": "651234", "description": "4-bell run step pairs"},
  {"stage": 6, "pattern": "125634", "description": "step pairs (no run)"},
  {"stage": 6, "pattern": "125643", "description": "step pairs (no run)"},
  {"stage": 6, "pattern": "126534", "description": "step pairs (no run)"},
  {"stage": 6, "pattern": "215634", "description": "step pairs (no run)"},
  {"stage": 6, "pattern": "215643", "description": "step pairs (no run)"},
  {"stage": 6, "pattern": "216534", "description": "step pairs (no run)"},
  {"stage": 6, "pattern": "341256", "description": "step pairs (no run)"},
  {"stage": 6, "pattern": "341265", "description": "step pairs (no run)"},
  {"stage": 6, "pattern": "342156", "description": "step pairs (no run)"},
  {"stage": 6, "pattern": "342165", "description": "step pairs (no run)"},
  {"stage": 6, "pattern": "346512", "description": "step pairs (no run)"},
  {"stage": 6, "pattern": "346521", "description": "step pairs (no run)"},
  {"stage": 6, "pattern": "431256", "description": "step pairs (no run)"},
  {"stage": 6, "pattern": "431265", "description": "step pairs (no run)"},
  {"stage": 6, "pattern": "435612", "description": "step pairs (no run)"},
  {"stage": 6, "pattern": "435621", "description": "step pairs (no run)"},
  {"stage": 6, "pattern": "436512", "description": "step pairs (no run)"},
  {"stage": 6, "pattern": "436521", "description": "step pairs (no run)"},
  {"stage": 6, "pattern": "561243", "description": "step pairs (no run)"},
  {"stage": 6, "pattern": "562134", "description": "step pairs (no run)"},
  {"stage": 6, "pattern": "562143", "description": "step pairs (no run)"},
  {"stage": 6, "pattern": "651243", "description": "step pairs (no run)"},
  {"stage": 6, "pattern": "652134", "description": "step pairs (no run)"},
  {"stage": 6, "pattern": "652143", "description": "step pairs (no run)"},
  {"stage": 6, "pattern": "132546", "description": "132546 (Priory/The Intermediate)"},
  {"stage": 6, "pattern": "645231", "description": "645231 (Reverse Priory)"},
  {"stage": 6, "pattern": "135246", "description": "135246 (Queens)"},
  {"stage": 6, "pattern": "531246", "description": "531246 (Kings)"},
  {"stage": 6, "pattern": "246135", "description": "Queens/Kings swap halves"},
  {"stage": 6, "pattern": "246531", "description": "Queens/Kings swap halves"},
  {"stage": 6, "pattern": "642531", "description": "Queens/Kings swap halves"},
  {"stage": 6, "pattern": "642135", "description": "Queens/Kings swap halves"},
  {"stage": 6, "pattern": "532146", "description": "532146 (Princes)"},
  {"stage": 6, "pattern": "142536", "description": "142536 (Tittums)"},
  {"stage": 6, "pattern": "142563", "description": "Tittums pair swap"},
  {"stage": 6, "pattern": "412563", "description": "Tittums pair swap"},
  
  {"stage": 6, "pattern": "415236", "description": "Tittums pair swap"},
  {"stage": 6, "pattern": "145263", "description": "Tittums pair swap"},
  {"stage": 6, "pattern": "415263", "description": "Tittums pair swap"},
  {"stage": 6, "pattern": "342516", "description": "342516 (Exploded Tittums)"},
  {"stage": 6, "pattern": "342561", "description": "Exploded Tittums pair swap"},
  {"stage": 6, "pattern": "432561", "description": "Exploded Tittums pair swap"},
  {"stage": 6, "pattern": "345216", "description": "Exploded Tittums pair swap"},
  {"stage": 6, "pattern": "435216", "description": "Exploded Tittums pair swap"},
  {"stage": 6, "pattern": "345261", "description": "Exploded Tittums pair swap"},
  {"stage": 6, "pattern": "435261", "description": "Exploded Tittums pair swap"},
  {"stage": 6, "pattern": "145236", "description": "145236 (Jacks)"},
  {"stage": 6, "pattern": "154326", "description": "154326 (Jokers/Devils)"},
  {"stage": 6, "pattern": "213546", "description": "213546 (Burdette)"},
  {"stage": 6, "pattern": "321456", "description": "321456 (See-saw)"},
  {"stage": 6, "pattern": "456123", "description": "See-saw/Saw-see variant"},
  {"stage": 6, "pattern": "456321", "description": "See-saw/Saw-see variant"},
  {"stage": 6, "pattern": "123654", "description": "See-saw/Saw-see variant"},
  {"stage": 6, "pattern": "321654", "description": "See-saw/Saw-see variant"},
  {"stage": 6, "pattern": "165432", "description": "5-bell run[s]"},
  {"stage": 6, "pattern": "234561", "description": "5-bell run[s]"},
  {"stage": 6, "pattern": "612345", "description": "5-bell run[s]"},
  {"stage": 6, "pattern": "543216", "description": "5-bell run[s]"},
  {"stage": 6, "pattern": "134562", "description": "4-bell run (not step pairs)"},
  {"stage": 6, "pattern": "265431", "description": "4-bell run (not step pairs)"},
  {"stage": 6, "pattern": "512346", "description": "4-bell run (not step pairs)"},
  {"stage": 6, "pattern": "623451", "description": "4-bell run (not step pairs)"},
  {"stage": 6, "pattern": "643215", "description": "4-bell run (not step pairs)"},
  {"stage": 6, "pattern": "162345", "description": "4-bell run (not step pairs)"},
  {"stage": 6, "pattern": "234516", "description": "4-bell run (not step pairs)"},
  {"stage": 6, "pattern": "543261", "description": "4-bell run (not step pairs)"},
  {"stage": 6, "pattern": "615432", "description": "4-bell run (not step pairs)"},
  {"stage": 6, "pattern": "1234", "description": "4-bell run[s]"},
  {"stage": 6, "pattern": "2345", "description": "4-bell run[s]"},
  {"stage": 6, "pattern": "3456", "description": "4-bell run[s]"},
  {"stage": 6, "pattern": "4321", "description": "4-bell run[s]"},
  {"stage": 6, "pattern": "5432", "description": "4-bell run[s]"},
  {"stage": 6, "pattern": "6543", "description": "4-bell run[s]"},
  {"stage": 6, "pattern": "65432", "description": "5-bell run[s]"},
  {"stage": 6, "pattern": "23456", "description": "5-bell run[s]"},
  {"stage": 6, "pattern": "12345", "description": "5-bell run[s]"},
  {"stage": 6, "pattern": "54321", "description": "5-bell run[s]"},

  {"stage": 8, "pattern": "12345678", "description": "named row"},
  {"stage": 8, "pattern": "12563478", "description": "named row"},
  {"stage": 8, "pattern": "12753468", "description": "named row"},
  {"stage": 8, "pattern": "13245768", "description": "named row"},
  {"stage": 8, "pattern": "13254768", "description": "named row"},
  {"stage": 8, "pattern": "13527468", "description": "named row"},
  {"stage": 8, "pattern": "13572468", "description": "named row"},
  {"stage": 8, "pattern": "14327658", "description": "named row"},
  {"stage": 8, "pattern": "15263748", "description": "named row"},
  {"stage": 8, "pattern": "16745238", "description": "named row"},
  {"stage": 8, "pattern": "17652438", "description": "named row"},
  {"stage": 8, "pattern": "17654328", "description": "named row"},
  {"stage": 8, "pattern": "31247568", "description": "named row"},
  {"stage": 8, "pattern": "43215678", "description": "named row"},
  {"stage": 8, "pattern": "56781234", "description": "named row"},
  {"stage": 8, "pattern": "45362718", "description": "named row"},
  {"stage": 8, "pattern": "65432178", "description": "named row"},
  {"stage": 8, "pattern": "75312468", "description": "named row"},
  {"stage": 8, "pattern": "75321468", "description": "named row"},
  {"stage": 8, "pattern": "87123456", "description": "named row"},
  {"stage": 8, "pattern": "87654321", "description": "named row"},
  {"stage": 8, "pattern": "1234567", "description": "7-bell run"},
  {"stage": 8, "pattern": "2345678", "description": "7-bell run"},
  {"stage": 8, "pattern": "7654321", "description": "7-bell run"},
  {"stage": 8, "pattern": "8765432", "description": "7-bell run"},
  {"stage": 8, "pattern": "123456", "description": "6-bell run"},
  {"stage": 8, "pattern": "234567", "description": "6-bell run"},
  {"stage": 8, "pattern": "345678", "description": "6-bell run"},
  {"stage": 8, "pattern": "654321", "description": "6-bell run"},
  {"stage": 8, "pattern": "765432", "description": "6-bell run"},
  {"stage": 8, "pattern": "876543", "description": "6-bell run"},
  {"stage": 8, "pattern": "21345678", "description": "step pairs or near miss"},
  {"stage": 8, "pattern": "13245678", "description": "step pairs or near miss"},
  {"stage": 8, "pattern": "12435678", "description": "step pairs or near miss"},
  {"stage": 8, "pattern": "12354678", "description": "step pairs or near miss"},
  {"stage": 8, "pattern": "12346578", "description": "step pairs or near miss"},
  {"stage": 8, "pattern": "12345768", "description": "step pairs or near miss"},
  {"stage": 8, "pattern": "12345687", "description": "step pairs or near miss"},
  {"stage": 8, "pattern": "78654321", "description": "step pairs or near miss"},
  {"stage": 8, "pattern": "86754321", "description": "step pairs or near miss"},
  {"stage": 8, "pattern": "87564321", "description": "step pairs or near miss"},
  {"stage": 8, "pattern": "87645321", "description": "step pairs or near miss"},
  {"stage": 8, "pattern": "87653421", "description": "step pairs or near miss"},
  {"stage": 8, "pattern": "87654231", "description": "step pairs or near miss"},
  {"stage": 8, "pattern": "87654312", "description": "step pairs or near miss"},
  {"stage": 8, "pattern": "12436578", "description": "step pairs or near miss"},
  {"stage": 8, "pattern": "21436578", "description": "step pairs or near miss"},
  {"stage": 8, "pattern": "12435687", "description": "step pairs or near miss"},
  {"stage": 8, "pattern": "21435687", "description": "step pairs or near miss"},
  {"stage": 8, "pattern": "12346587", "description": "step pairs or near miss"},
  {"stage": 8, "pattern": "21346587", "description": "step pairs or near miss"},
  {"stage": 8, "pattern": "12436587", "description": "step pairs or near miss"},
  {"stage": 8, "pattern": "21436587", "description": "step pairs or near miss"},
  {"stage": 8, "pattern": "78563421", "description": "step pairs or near miss"},
  {"stage": 8, "pattern": "87563421", "description": "step pairs or near miss"},
  {"stage": 8, "pattern": "78564312", "description": "step pairs or near miss"},
  {"stage": 8, "pattern": "87564312", "description": "step pairs or near miss"},
  {"stage": 8, "pattern": "78653412", "description": "step pairs or near miss"},
  {"stage": 8, "pattern": "87653412", "description": "step pairs or near miss"},
  {"stage": 8, "pattern": "78563412", "description": "step pairs or near miss"},
  {"stage": 8, "pattern": "87563412", "description": "step pairs or near miss"},
  {"stage": 8, "pattern": "18765432", "description": "7-bell run"},
  {"stage": 8, "pattern": "23456781", "description": "7-bell run"},
  {"stage": 8, "pattern": "81234567", "description": "7-bell run"},
  {"stage": 8, "pattern": "76543218", "description": "7-bell run"},
  {"stage": 8, "pattern": "23145678", "description": "misplaced treble/tenor"},
  {"stage": 8, "pattern": "23415678", "description": "misplaced treble/tenor"},
  {"stage": 8, "pattern": "23451678", "description": "misplaced treble/tenor"},
  {"stage": 8, "pattern": "23456178", "description": "misplaced treble/tenor"},
  {"stage": 8, "pattern": "23456718", "description": "misplaced treble/tenor"},
  {"stage": 8, "pattern": "87654132", "description": "misplaced treble/tenor"},
  {"stage": 8, "pattern": "87651432", "description": "misplaced treble/tenor"},
  {"stage": 8, "pattern": "87615432", "description": "misplaced treble/tenor"},
  {"stage": 8, "pattern": "87165432", "description": "misplaced treble/tenor"},
  {"stage": 8, "pattern": "81765432", "description": "misplaced treble/tenor"},
  {"stage": 8, "pattern": "76854321", "description": "misplaced treble/tenor"},
  {"stage": 8, "pattern": "76584321", "description": "misplaced treble/tenor"},
  {"stage": 8, "pattern": "76548321", "description": "misplaced treble/tenor"},
  {"stage": 8, "pattern": "76543821", "description": "misplaced treble/tenor"},
  {"stage": 8, "pattern": "76543281", "description": "misplaced treble/tenor"},
  {"stage": 8, "pattern": "35724618", "description": ""},
  {"stage": 8, "pattern": "35724681", "description": ""},
  {"stage": 8, "pattern": "35241678", "description": ""},
  {"stage": 8, "pattern": "15263748", "description": "tittums pairs"},
  {"stage": 8, "pattern": "51267384", "description": "tittums pairs"},
  {"stage": 8, "pattern": "15623748", "description": "tittums pairs"},
  {"stage": 8, "pattern": "15627384", "description": "tittums pairs"},
  {"stage": 8, "pattern": "51263748", "description": "tittums pairs"},
  {"stage": 8, "pattern": "51627348", "description": "tittums pairs"},
  {"stage": 8, "pattern": "15263784", "description": "tittums pairs"},
  {"stage": 8, "pattern": "15627348", "description": "tittums pairs"},
  {"stage": 8, "pattern": "51263784", "description": "tittums pairs"},
  {"stage": 8, "pattern": "51627384", "description": "tittums pairs"},
  {"stage": 8, "pattern": "15267384", "description": "tittums pairs"},
  {"stage": 8, "pattern": "51623748", "description": "tittums pairs"},
  {"stage": 8, "pattern": "51267348", "description": "tittums pairs"},
  {"stage": 8, "pattern": "15623784", "description": "tittums pairs"},
  {"stage": 8, "pattern": "15267348", "description": "tittums pairs"},
  {"stage": 8, "pattern": "51623784", "description": "tittums pairs"},
  {"stage": 8, "pattern": "48376251", "description": "tittums pairs"},
  {"stage": 8, "pattern": "84732615", "description": "tittums pairs"},
  {"stage": 8, "pattern": "48372615", "description": "tittums pairs"},
  {"stage": 8, "pattern": "84736251", "description": "tittums pairs"},
  {"stage": 8, "pattern": "84372651", "description": "tittums pairs"},
  {"stage": 8, "pattern": "48736215", "description": "tittums pairs"},
  {"stage": 8, "pattern": "84372615", "description": "tittums pairs"},
  {"stage": 8, "pattern": "48736251", "description": "tittums pairs"},
  {"stage": 8, "pattern": "48372651", "description": "tittums pairs"},
  {"stage": 8, "pattern": "84736215", "description": "tittums pairs"},
  {"stage": 8, "pattern": "48376215", "description": "tittums pairs"},
  {"stage": 8, "pattern": "84732651", "description": "tittums pairs"},
  {"stage": 8, "pattern": "84376251", "description": "tittums pairs"},
  {"stage": 8, "pattern": "48732615", "description": "tittums pairs"},
  {"stage": 8, "pattern": "84376215", "description": "tittums pairs"},
  {"stage": 8, "pattern": "48732651", "description": "tittums pairs"},
  {"stage": 8, "pattern": "45367218", "description": "explodey"},
  {"stage": 8, "pattern": "54632781", "description": "explodey"},
  {"stage": 8, "pattern": "54367218", "description": "explodey"},
  {"stage": 8, "pattern": "45632781", "description": "explodey"},
  {"stage": 8, "pattern": "45367281", "description": "explodey"},
  {"stage": 8, "pattern": "54632718", "description": "explodey"},
  {"stage": 8, "pattern": "54367281", "description": "explodey"},
  {"stage": 8, "pattern": "45632718", "description": "explodey"},
  {"stage": 8, "pattern": "45637281", "description": "explodey"},
  {"stage": 8, "pattern": "54362718", "description": "explodey"},
  {"stage": 8, "pattern": "54637281", "description": "explodey"},
  {"stage": 8, "pattern": "45362718", "description": "explodey"},
  {"stage": 8, "pattern": "45637218", "description": "explodey"},
  {"stage": 8, "pattern": "54362781", "description": "explodey"},
  {"stage": 8, "pattern": "54637218", "description": "explodey"},
  {"stage": 8, "pattern": "45362781", "description": "explodey"},
  {"stage": 8, "pattern": "35467281", "description": "explodey"},
  {"stage": 8, "pattern": "53642718", "description": "explodey"},
  {"stage": 8, "pattern": "53467281", "description": "explodey"},
  {"stage": 8, "pattern": "35642718", "description": "explodey"},
  {"stage": 8, "pattern": "35647281", "description": "explodey"},
  {"stage": 8, "pattern": "53462718", "description": "explodey"},
  {"stage": 8, "pattern": "53647281", "description": "explodey"},
  {"stage": 8, "pattern": "35462718", "description": "explodey"},
  {"stage": 8, "pattern": "35647218", "description": "explodey"},
  {"stage": 8, "pattern": "53462781", "description": "explodey"},
  {"stage": 8, "pattern": "53647218", "description": "explodey"},
  {"stage": 8, "pattern": "35462781", "description": "explodey"},
  {"stage": 8, "pattern": "35467218", "description": "explodey"},
  {"stage": 8, "pattern": "53642781", "description": "explodey"},
  {"stage": 8, "pattern": "53467218", "description": "explodey"},
  {"stage": 8, "pattern": "35642781", "description": "explodey"},
  {"stage": 8, "pattern": "43657281", "description": "explodey"},
  {"stage": 8, "pattern": "43652718", "description": "explodey"},
  {"stage": 8, "pattern": "34657218", "description": "explodey"},
  {"stage": 8, "pattern": "43562781", "description": "explodey"},
  {"stage": 8, "pattern": "43652781", "description": "explodey"},
  {"stage": 8, "pattern": "34657281", "description": "explodey"},
  {"stage": 8, "pattern": "43562718", "description": "explodey"},
  {"stage": 8, "pattern": "43567281", "description": "explodey"},
  {"stage": 8, "pattern": "34652718", "description": "explodey"},
  {"stage": 8, "pattern": "43657218", "description": "explodey"},
  {"stage": 8, "pattern": "43567218", "description": "explodey"},
  {"stage": 8, "pattern": "34652781", "description": "explodey"},
  {"stage": 8, "pattern": "46357218", "description": "explodey"},
  {"stage": 8, "pattern": "64532781", "description": "explodey"},
  {"stage": 8, "pattern": "46537218", "description": "explodey"},
  {"stage": 8, "pattern": "64352781", "description": "explodey"},
  {"stage": 8, "pattern": "64357218", "description": "explodey"},
  {"stage": 8, "pattern": "46532781", "description": "explodey"},
  {"stage": 8, "pattern": "64537218", "description": "explodey"},
  {"stage": 8, "pattern": "46352781", "description": "explodey"},
  {"stage": 8, "pattern": "64537281", "description": "explodey"},
  {"stage": 8, "pattern": "46352718", "description": "explodey"},
  {"stage": 8, "pattern": "46357281", "description": "explodey"},
  {"stage": 8, "pattern": "64532718", "description": "explodey"},
  {"stage": 8, "pattern": "64357281", "description": "explodey"},
  {"stage": 8, "pattern": "46532718", "description": "explodey"},
  {"stage": 8, "pattern": "46537281", "description": "explodey"},
  {"stage": 8, "pattern": "64352718", "description": "explodey"},
  {"stage": 8, "pattern": "65347218", "description": "explodey"},
  {"stage": 8, "pattern": "56432781", "description": "explodey"},
  {"stage": 8, "pattern": "56347218", "description": "explodey"},
  {"stage": 8, "pattern": "56347281", "description": "explodey"},
  {"stage": 8, "pattern": "65347281", "description": "explodey"},
  {"stage": 8, "pattern": "56432718", "description": "explodey"},
  {"stage": 8, "pattern": "56342781", "description": "explodey"},
  {"stage": 8, "pattern": "56437218", "description": "explodey"},
  {"stage": 8, "pattern": "65342781", "description": "explodey"},
  {"stage": 8, "pattern": "56437281", "description": "explodey"},
  {"stage": 8, "pattern": "65342718", "description": "explodey"},
  {"stage": 8, "pattern": "56342718", "description": "explodey"},
  {"stage": 8, "pattern": "xxxx2718", "description": ""},
  {"stage": 8, "pattern": "xxxx2781", "description": ""},
  {"stage": 8, "pattern": "xxxx7218", "description": ""},
  {"stage": 8, "pattern": "xxxx7281", "description": ""},
  {"stage": 8, "pattern": "xxxx2516", "description": ""},
  {"stage": 8, "pattern": "xxxx2561", "description": ""},
  {"stage": 8, "pattern": "xxxx5216", "description": ""},
  {"stage": 8, "pattern": "xxxx5261", "description": ""},
  {"stage": 8, "pattern": "xxxx2716", "description": ""},
  {"stage": 8, "pattern": "xxxx2761", "description": ""},
  {"stage": 8, "pattern": "xxxx7216", "description": ""},
  {"stage": 8, "pattern": "xxxx7261", "description": ""},
  {"stage": 8, "pattern": "xxxx1468", "description": ""},
  {"stage": 8, "pattern": "xxxx6418", "description": ""},
  {"stage": 8, "pattern": "xxxx8641", "description": ""},
  {"stage": 8, "pattern": "xxxx4681", "description": ""},
  {"stage": 8, "pattern": "xxxx4678", "description": ""},
  {"stage": 8, "pattern": "xxxx4568", "description": ""},
  {"stage": 8, "pattern": "xxxx7468", "description": ""},
  {"stage": 8, "pattern": "xxxx1678", "description": ""},
  {"stage": 8, "pattern": "xxxx1456", "description": ""}
]
